velib/__init__.py
velib/bitmap.py
velib/crypto.py
velib/decorators.py
velib/dot_dict.py
velib/exception.py
velib/hashers.py
velib/log.py
velib/middleware.py
velib/network.py
velib/paginator.py
velib/prepare.py
velib/response.py
velib/settings.py
velib/telegram.py
velib/tokenizator.py
velib/utils.py
velib-0.1.1.dist-info/METADATA
velib-0.1.1.dist-info/WHEEL
velib-0.1.1.dist-info/top_level.txt
velib-0.1.1.dist-info/RECORD
