Metadata-Version: 2.1
Name: velib
Version: 0.1.1
Summary: ve common library
Home-page: https://ve.com
Author: ve
Author-email: 
License: MIT
Classifier: Development Status :: 5 - Production/Stable
Classifier: Intended Audience :: Developers
Classifier: Topic :: Software Development :: Build Tools
Classifier: License :: Other/Proprietary License
Classifier: Programming Language :: Python :: 3.11
